{
  "companies": [
    {
      "name": "inVRsion",
      "users": [
        "Lori",
        "Marco"        
      ]
    },
    {
      "name": "Twinbru",
      "users": [
        "John",
        "Olga",
        "Nathan",
        "Mattia"
      ]
    },
    {
      "name": "Twinbru",
      "users": [
        "John",
        "Olga",
        "Nathan",
        "Mattia"
      ]
    },
    {
      "name": "Twinbru",
      "users": [
        "John",
        "Olga",
        "Nathan",
        "Mattia"
      ]
    },
        {
      "name": "Twinbru",
      "users": [
        "John",
        "Olga",
        "Nathan",
        "Mattia"
      ]
    }
  ]
}
